sdp_test_package_vk/main.py
sdp_test_package_vk/mod1.py
sdp_test_package_vk-0.1.dist-info/DESCRIPTION.rst
sdp_test_package_vk-0.1.dist-info/METADATA
sdp_test_package_vk-0.1.dist-info/RECORD
sdp_test_package_vk-0.1.dist-info/WHEEL
sdp_test_package_vk-0.1.dist-info/metadata.json
sdp_test_package_vk-0.1.dist-info/top_level.txt
