Metadata-Version: 2.0
Name: sdp-test-package-vk
Version: 0.1
Summary: A random test lib
Home-page: UNKNOWN
Author: Vijay Kulkarni
Author-email: vijaykulkarni.u@gmail.com
License: UNKNOWN
Keywords: testing,example
Platform: UNKNOWN
